Excel10library/Excel10Library.py
Excel10library/__init__.py
Excel10library/version.py
robotframework_excel10library-0.0.6.dist-info/METADATA
robotframework_excel10library-0.0.6.dist-info/RECORD
robotframework_excel10library-0.0.6.dist-info/WHEEL
robotframework_excel10library-0.0.6.dist-info/top_level.txt
